quiet_py_wasm/__init__.py
quiet_py_wasm/quiet-profiles.json
quiet_py_wasm/quiet.py
quiet_py_wasm/quiet.wasm
quiet_py_wasm/receiver.py
quiet_py_wasm/transmitter.py
quiet_py_wasm/utils.py
quiet_py_wasm-0.1.3.dist-info/WHEEL
quiet_py_wasm-0.1.3.dist-info/METADATA
quiet_py_wasm-0.1.3.dist-info/RECORD
